starttf_extra/__init__.py
starttf_extra/layers/__init__.py
starttf_extra/layers/normalization.py
starttf_extra/layers/rezoom.py
starttf_extra/layers/upsampling.py
starttf_extra/models/__init__.py
starttf_extra/models/backbones/__init__.py
starttf_extra/models/backbones/fpn_backbone.py
starttf_extra/models/backbones/overfeat_backbone.py
starttf_extra/models/backbones/ssd_backbone.py
starttf_extra/models/backbones/yolo_v2_backbone.py
starttf_extra-1.0.0.dist-info/METADATA
starttf_extra-1.0.0.dist-info/WHEEL
starttf_extra-1.0.0.dist-info/top_level.txt
starttf_extra-1.0.0.dist-info/RECORD
