Metadata-Version: 2.1
Name: starttf-extra
Version: 1.0.0
Summary: Addons for starttf that are not all MIT.
Home-page: https://github.com/penguinmenac3/starttf_extra
Author: Michael Fuerst
Author-email: mail@michaelfuerst.de
License: BSD
Download-URL: https://github.com/penguinmenac3/starttf_extra/tarball/1.0.0
Platform: UNKNOWN
Classifier: Development Status :: 3 - Alpha
Classifier: Intended Audience :: Developers
Classifier: Programming Language :: Python
Requires-Dist: starttf
